pyoffers/__init__.py
pyoffers/api.py
pyoffers/exceptions.py
pyoffers/logging.py
pyoffers/utils.py
pyoffers/models/__init__.py
pyoffers/models/advertiser.py
pyoffers/models/affiliate.py
pyoffers/models/conversion.py
pyoffers/models/core.py
pyoffers/models/country.py
pyoffers/models/goal.py
pyoffers/models/offer.py
pyoffers/models/offer_file.py
pyoffers/models/raw_log.py
pyoffers/models/tags.py
pyoffers-0.7.0.dist-info/LICENSE
pyoffers-0.7.0.dist-info/METADATA
pyoffers-0.7.0.dist-info/WHEEL
pyoffers-0.7.0.dist-info/top_level.txt
pyoffers-0.7.0.dist-info/RECORD
