Metadata-Version: 2.1
Name: pyoffers
Version: 0.7.0
Summary: Python client library for HasOffers API
Home-page: https://github.com/Stranger6667/pyoffers
Author: Dmitry Dygalo
Author-email: dadygalo@gmail.com
Maintainer: Dmitry Dygalo
Maintainer-email: dadygalo@gmail.com
License: MIT
Keywords: hasoffers,api,client
Platform: UNKNOWN
Classifier: Development Status :: 4 - Beta
Classifier: Environment :: Console
Classifier: Intended Audience :: Developers
Classifier: Operating System :: OS Independent
Classifier: License :: OSI Approved :: MIT License
Classifier: Programming Language :: Python
Classifier: Programming Language :: Python :: 3 :: Only
Classifier: Programming Language :: Python :: 3.5
Classifier: Programming Language :: Python :: 3.6
Classifier: Programming Language :: Python :: 3.7
Classifier: Programming Language :: Python :: 3.8
Classifier: Programming Language :: Python :: Implementation :: CPython
Classifier: Programming Language :: Python :: Implementation :: PyPy
Requires-Dist: requests
